tice/__init__.py
tice-2.1.dist-info/METADATA
tice-2.1.dist-info/WHEEL
tice-2.1.dist-info/top_level.txt
tice-2.1.dist-info/RECORD
