Metadata-Version: 2.1
Name: tice
Version: 2.1
Summary: Tic-Tac-Toe in Python
Home-page: https://github.com/tic-tac-toe-in-python
Author: tice
License: MIT
Keywords: tic-tac-toe,ttt,ai,multiplayer,min,max,minmax,minimax
Classifier: Development Status :: 1 - Planning
Classifier: Development Status :: 2 - Pre-Alpha
Classifier: Development Status :: 3 - Alpha
Classifier: Development Status :: 4 - Beta
Classifier: Development Status :: 5 - Production/Stable
Classifier: Intended Audience :: Developers
Classifier: Topic :: Software Development :: Build Tools
Classifier: License :: OSI Approved :: MIT License
Classifier: Programming Language :: Python :: 3
